LICENSE
MANIFEST.in
README.rst
requirements-lint.txt
requirements-old.txt
requirements-optional.txt
requirements-test-old.txt
requirements-test.txt
requirements.txt
setup.cfg
setup.py
ntclient/__init__.py
ntclient/__main__.py
ntclient/argparser/__init__.py
ntclient/argparser/funcs.py
ntclient/argparser/types.py
ntclient/core/__init__.py
ntclient/core/nnest.py
ntclient/core/nnr2.py
ntclient/core/nutprogbar.py
ntclient/models/__init__.py
ntclient/ntsqlite/__init__.py
ntclient/ntsqlite/sql/__init__.py
ntclient/ntsqlite/sql/__main__.py
ntclient/ntsqlite/sql/functions.sql
ntclient/ntsqlite/sql/tables.sql
ntclient/ntsqlite/sql/data/bf_eq.csv
ntclient/ntsqlite/sql/data/bmr_eq.csv
ntclient/ntsqlite/sql/data/meal_name.csv
ntclient/ntsqlite/sql/data/rda.csv
ntclient/ntsqlite/sql/data/version.csv
ntclient/persistence/__init__.py
ntclient/persistence/sql/__init__.py
ntclient/persistence/sql/nt/__init__.py
ntclient/persistence/sql/nt/funcs.py
ntclient/persistence/sql/usda/__init__.py
ntclient/persistence/sql/usda/funcs.py
ntclient/resources/recipe/dinner/burrito-bowl.csv
ntclient/resources/recipe/dinner/grass-fed-burger.csv
ntclient/resources/recipe/snack/baked-potato-wedges.csv
ntclient/resources/recipe/snack/buckwheat-pancake.csv
ntclient/resources/recipe/snack/fruit-smoothie.csv
ntclient/resources/recipe/tmp/food_amounts.csv
ntclient/resources/recipe/tmp/names.csv
ntclient/resources/recipe/tmp/servings.csv
ntclient/services/__init__.py
ntclient/services/analyze.py
ntclient/services/calculate.py
ntclient/services/usda.py
ntclient/services/recipe/__init__.py
ntclient/services/recipe/csv_utils.py
ntclient/services/recipe/utils.py
ntclient/utils/__init__.py
ntclient/utils/colors.py
ntclient/utils/exceptions.py
ntclient/utils/tree.py
nutra.egg-info/PKG-INFO
nutra.egg-info/SOURCES.txt
nutra.egg-info/dependency_links.txt
nutra.egg-info/entry_points.txt
nutra.egg-info/not-zip-safe
nutra.egg-info/requires.txt
nutra.egg-info/top_level.txt
tests/services/__init__.py
tests/services/test_calculate.py
tests/services/test_recipe.py
tests/utils/__init__.py
tests/utils/test_tree.py