Metadata-Version: 2.1
Name: nutra
Version: 0.2.6
Summary: Home and office nutrient tracking software
Home-page: https://github.com/nutratech/cli
Author: Shane Jaroch
Author-email: chown_tee@proton.me
License: GPL v3
Platform: linux
Platform: darwin
Platform: win32
Classifier: Environment :: Console
Classifier: Intended Audience :: End Users/Desktop
Classifier: Intended Audience :: Science/Research
Classifier: Intended Audience :: Healthcare Industry
Classifier: Intended Audience :: Education
Classifier: Development Status :: 3 - Alpha
Classifier: Natural Language :: English
Classifier: License :: OSI Approved :: GNU General Public License v3 (GPLv3)
Classifier: Framework :: Flake8
Classifier: Framework :: Pytest
Classifier: Operating System :: OS Independent
Classifier: Operating System :: Microsoft :: Windows :: Windows XP
Classifier: Operating System :: Microsoft :: Windows :: Windows 10
Classifier: Operating System :: MacOS :: MacOS X
Classifier: Operating System :: POSIX :: Linux
Classifier: Programming Language :: Python :: Implementation :: CPython
Classifier: Programming Language :: Python :: Implementation :: PyPy
Classifier: Programming Language :: Python :: 3 :: Only
Classifier: Programming Language :: Python :: 3.4
Classifier: Programming Language :: Python :: 3.11
Classifier: Programming Language :: SQL
Classifier: Programming Language :: Unix Shell
Requires-Python: >=3.4.3
License-File: LICENSE
